decryptpdf/__init__.py
decryptpdf/__main__.py
decryptpdf/_main.py
decryptpdf/cli.py
decryptpdf/py.typed
decryptpdf-1.0.0.dist-info/licenses/LICENSE
decryptpdf-1.0.0.dist-info/METADATA
decryptpdf-1.0.0.dist-info/WHEEL
decryptpdf-1.0.0.dist-info/entry_points.txt
decryptpdf-1.0.0.dist-info/top_level.txt
decryptpdf-1.0.0.dist-info/RECORD
