Metadata-Version: 2.4
Name: decryptpdf
Version: 1.0.0
Summary: Simple CLI tool for decrypting PDF files.
Author-email: 34j <34j.95a2p@simplelogin.com>
License: MIT
Project-URL: Bug Tracker, https://github.com/34j/decryptpdf/issues
Project-URL: Changelog, https://github.com/34j/decryptpdf/blob/main/CHANGELOG.md
Project-URL: documentation, https://decryptpdf.readthedocs.io
Project-URL: repository, https://github.com/34j/decryptpdf
Classifier: Development Status :: 2 - Pre-Alpha
Classifier: Intended Audience :: Developers
Classifier: Natural Language :: English
Classifier: Operating System :: OS Independent
Classifier: Programming Language :: Python :: 3.9
Classifier: Programming Language :: Python :: 3.10
Classifier: Programming Language :: Python :: 3.11
Classifier: Programming Language :: Python :: 3.12
Classifier: Programming Language :: Python :: 3.13
Classifier: Topic :: Software Development :: Libraries
Requires-Python: >=3.9
License-File: LICENSE
Requires-Dist: pikepdf>=9.8.1
Requires-Dist: rich>=10
Requires-Dist: tqdm>=4.67.1
Requires-Dist: typer<1,>=0.15
Dynamic: license-file
